mapraline/__init__.py
mapraline/cmd.py
mapraline/prosite.py
mapraline/scores.py
mapraline/component/__init__.py
mapraline/component/predict.py
ma_praline-1.1.0.dist-info/LICENSE
ma_praline-1.1.0.dist-info/METADATA
ma_praline-1.1.0.dist-info/WHEEL
ma_praline-1.1.0.dist-info/entry_points.txt
ma_praline-1.1.0.dist-info/top_level.txt
ma_praline-1.1.0.dist-info/RECORD
