Metadata-Version: 2.1
Name: ma-praline
Version: 1.1.0
Summary: PRALINE workflow for motif-aware alignment (MA-PRALINE).
Home-page: https://github.com/ibivu/MA-PRALINE/
Author: Maurits Dijkstra
Author-email: mauritsdijkstra@gmail.com
License: GPLv2
Platform: UNKNOWN
Classifier: Development Status :: 5 - Production/Stable
Classifier: License :: OSI Approved :: GNU General Public License v2 (GPLv2)
Classifier: Environment :: Console
Classifier: Intended Audience :: Science/Research
Classifier: Programming Language :: Python :: 2.7
Classifier: Programming Language :: Python :: 3.6
Requires-Python: >=2.7,!=3.0.*,!=3.1.*,!=3.2.*,!=3.2.*,!=3.3.*,!=3.4.*
